{
	"id": "c0d01c64-b09d-472b-a74f-ed758008d75d",
	"prevId": "00000000-0000-0000-0000-000000000000",
	"version": "7",
	"dialect": "postgresql",
	"tables": {
		"public.files": {
			"name": "files",
			"schema": "",
			"columns": {
				"id": {
					"name": "id",
					"type": "uuid",
					"primaryKey": true,
					"notNull": true,
					"default": "gen_random_uuid()"
				},
				"resource_id": {
					"name": "resource_id",
					"type": "uuid",
					"primaryKey": false,
					"notNull": true
				},
				"mime_type": {
					"name": "mime_type",
					"type": "varchar(255)",
					"primaryKey": false,
					"notNull": true
				},
				"size": {
					"name": "size",
					"type": "bigint",
					"primaryKey": false,
					"notNull": true
				}
			},
			"indexes": {},
			"foreignKeys": {
				"files_resource_id_resources_id_fk": {
					"name": "files_resource_id_resources_id_fk",
					"tableFrom": "files",
					"tableTo": "resources",
					"columnsFrom": ["resource_id"],
					"columnsTo": ["id"],
					"onDelete": "no action",
					"onUpdate": "no action"
				}
			},
			"compositePrimaryKeys": {},
			"uniqueConstraints": {},
			"policies": {},
			"checkConstraints": {},
			"isRLSEnabled": false
		},
		"public.folders": {
			"name": "folders",
			"schema": "",
			"columns": {
				"id": {
					"name": "id",
					"type": "uuid",
					"primaryKey": true,
					"notNull": true,
					"default": "gen_random_uuid()"
				},
				"resource_id": {
					"name": "resource_id",
					"type": "uuid",
					"primaryKey": false,
					"notNull": true
				}
			},
			"indexes": {},
			"foreignKeys": {
				"folders_resource_id_resources_id_fk": {
					"name": "folders_resource_id_resources_id_fk",
					"tableFrom": "folders",
					"tableTo": "resources",
					"columnsFrom": ["resource_id"],
					"columnsTo": ["id"],
					"onDelete": "no action",
					"onUpdate": "no action"
				}
			},
			"compositePrimaryKeys": {},
			"uniqueConstraints": {},
			"policies": {},
			"checkConstraints": {},
			"isRLSEnabled": false
		},
		"public.groups": {
			"name": "groups",
			"schema": "",
			"columns": {
				"id": {
					"name": "id",
					"type": "uuid",
					"primaryKey": true,
					"notNull": true,
					"default": "gen_random_uuid()"
				},
				"name": {
					"name": "name",
					"type": "varchar(255)",
					"primaryKey": false,
					"notNull": true
				},
				"description": {
					"name": "description",
					"type": "text",
					"primaryKey": false,
					"notNull": false
				},
				"created_by": {
					"name": "created_by",
					"type": "uuid",
					"primaryKey": false,
					"notNull": true
				},
				"updated_at": {
					"name": "updated_at",
					"type": "timestamp",
					"primaryKey": false,
					"notNull": true,
					"default": "now()"
				},
				"created_at": {
					"name": "created_at",
					"type": "timestamp",
					"primaryKey": false,
					"notNull": true,
					"default": "now()"
				},
				"deleted_at": {
					"name": "deleted_at",
					"type": "timestamp",
					"primaryKey": false,
					"notNull": false
				}
			},
			"indexes": {},
			"foreignKeys": {
				"groups_created_by_users_id_fk": {
					"name": "groups_created_by_users_id_fk",
					"tableFrom": "groups",
					"tableTo": "users",
					"columnsFrom": ["created_by"],
					"columnsTo": ["id"],
					"onDelete": "no action",
					"onUpdate": "no action"
				}
			},
			"compositePrimaryKeys": {},
			"uniqueConstraints": {},
			"policies": {},
			"checkConstraints": {},
			"isRLSEnabled": false
		},
		"public.resource_owners": {
			"name": "resource_owners",
			"schema": "",
			"columns": {
				"id": {
					"name": "id",
					"type": "uuid",
					"primaryKey": true,
					"notNull": true,
					"default": "gen_random_uuid()"
				},
				"resource_id": {
					"name": "resource_id",
					"type": "uuid",
					"primaryKey": false,
					"notNull": true
				},
				"user_id": {
					"name": "user_id",
					"type": "uuid",
					"primaryKey": false,
					"notNull": true
				},
				"updated_at": {
					"name": "updated_at",
					"type": "timestamp",
					"primaryKey": false,
					"notNull": true,
					"default": "now()"
				},
				"created_at": {
					"name": "created_at",
					"type": "timestamp",
					"primaryKey": false,
					"notNull": true,
					"default": "now()"
				},
				"deleted_at": {
					"name": "deleted_at",
					"type": "timestamp",
					"primaryKey": false,
					"notNull": false
				}
			},
			"indexes": {},
			"foreignKeys": {
				"resource_owners_resource_id_resources_id_fk": {
					"name": "resource_owners_resource_id_resources_id_fk",
					"tableFrom": "resource_owners",
					"tableTo": "resources",
					"columnsFrom": ["resource_id"],
					"columnsTo": ["id"],
					"onDelete": "no action",
					"onUpdate": "no action"
				},
				"resource_owners_user_id_users_id_fk": {
					"name": "resource_owners_user_id_users_id_fk",
					"tableFrom": "resource_owners",
					"tableTo": "users",
					"columnsFrom": ["user_id"],
					"columnsTo": ["id"],
					"onDelete": "no action",
					"onUpdate": "no action"
				}
			},
			"compositePrimaryKeys": {},
			"uniqueConstraints": {
				"resource_owners_resourceId_unique": {
					"name": "resource_owners_resourceId_unique",
					"nullsNotDistinct": false,
					"columns": ["resource_id"]
				}
			},
			"policies": {},
			"checkConstraints": {},
			"isRLSEnabled": false
		},
		"public.resources": {
			"name": "resources",
			"schema": "",
			"columns": {
				"id": {
					"name": "id",
					"type": "uuid",
					"primaryKey": true,
					"notNull": true,
					"default": "gen_random_uuid()"
				},
				"resource_type": {
					"name": "resource_type",
					"type": "resource_type",
					"typeSchema": "public",
					"primaryKey": false,
					"notNull": true
				},
				"parent_id": {
					"name": "parent_id",
					"type": "uuid",
					"primaryKey": false,
					"notNull": false
				},
				"name": {
					"name": "name",
					"type": "varchar(255)",
					"primaryKey": false,
					"notNull": true
				},
				"path": {
					"name": "path",
					"type": "text",
					"primaryKey": false,
					"notNull": true
				},
				"status": {
					"name": "status",
					"type": "resource_status",
					"typeSchema": "public",
					"primaryKey": false,
					"notNull": true,
					"default": "'active'"
				},
				"is_favorite": {
					"name": "is_favorite",
					"type": "boolean",
					"primaryKey": false,
					"notNull": true,
					"default": false
				},
				"updated_at": {
					"name": "updated_at",
					"type": "timestamp",
					"primaryKey": false,
					"notNull": true,
					"default": "now()"
				},
				"created_at": {
					"name": "created_at",
					"type": "timestamp",
					"primaryKey": false,
					"notNull": true,
					"default": "now()"
				},
				"deleted_at": {
					"name": "deleted_at",
					"type": "timestamp",
					"primaryKey": false,
					"notNull": false
				}
			},
			"indexes": {},
			"foreignKeys": {
				"resources_parent_id_resources_id_fk": {
					"name": "resources_parent_id_resources_id_fk",
					"tableFrom": "resources",
					"tableTo": "resources",
					"columnsFrom": ["parent_id"],
					"columnsTo": ["id"],
					"onDelete": "no action",
					"onUpdate": "no action"
				}
			},
			"compositePrimaryKeys": {},
			"uniqueConstraints": {},
			"policies": {},
			"checkConstraints": {},
			"isRLSEnabled": false
		},
		"public.resource_shared": {
			"name": "resource_shared",
			"schema": "",
			"columns": {
				"id": {
					"name": "id",
					"type": "uuid",
					"primaryKey": true,
					"notNull": true,
					"default": "gen_random_uuid()"
				},
				"resource_id": {
					"name": "resource_id",
					"type": "uuid",
					"primaryKey": false,
					"notNull": true
				},
				"entity_id": {
					"name": "entity_id",
					"type": "uuid",
					"primaryKey": false,
					"notNull": true
				},
				"entity_type": {
					"name": "entity_type",
					"type": "entity_type",
					"typeSchema": "public",
					"primaryKey": false,
					"notNull": true
				},
				"access_level": {
					"name": "access_level",
					"type": "access_level",
					"typeSchema": "public",
					"primaryKey": false,
					"notNull": true
				},
				"shared_by": {
					"name": "shared_by",
					"type": "uuid",
					"primaryKey": false,
					"notNull": true
				},
				"expires_at": {
					"name": "expires_at",
					"type": "timestamp",
					"primaryKey": false,
					"notNull": false
				},
				"updated_at": {
					"name": "updated_at",
					"type": "timestamp",
					"primaryKey": false,
					"notNull": true,
					"default": "now()"
				},
				"created_at": {
					"name": "created_at",
					"type": "timestamp",
					"primaryKey": false,
					"notNull": true,
					"default": "now()"
				},
				"deleted_at": {
					"name": "deleted_at",
					"type": "timestamp",
					"primaryKey": false,
					"notNull": false
				}
			},
			"indexes": {},
			"foreignKeys": {
				"resource_shared_resource_id_resources_id_fk": {
					"name": "resource_shared_resource_id_resources_id_fk",
					"tableFrom": "resource_shared",
					"tableTo": "resources",
					"columnsFrom": ["resource_id"],
					"columnsTo": ["id"],
					"onDelete": "no action",
					"onUpdate": "no action"
				},
				"resource_shared_shared_by_users_id_fk": {
					"name": "resource_shared_shared_by_users_id_fk",
					"tableFrom": "resource_shared",
					"tableTo": "users",
					"columnsFrom": ["shared_by"],
					"columnsTo": ["id"],
					"onDelete": "no action",
					"onUpdate": "no action"
				}
			},
			"compositePrimaryKeys": {},
			"uniqueConstraints": {
				"resource_shared_resourceId_entityId_entityType_unique": {
					"name": "resource_shared_resourceId_entityId_entityType_unique",
					"nullsNotDistinct": false,
					"columns": ["resource_id", "entity_id", "entity_type"]
				}
			},
			"policies": {},
			"checkConstraints": {},
			"isRLSEnabled": false
		},
		"public.user_groups": {
			"name": "user_groups",
			"schema": "",
			"columns": {
				"id": {
					"name": "id",
					"type": "uuid",
					"primaryKey": false,
					"notNull": true,
					"default": "gen_random_uuid()"
				},
				"user_id": {
					"name": "user_id",
					"type": "uuid",
					"primaryKey": false,
					"notNull": true
				},
				"group_id": {
					"name": "group_id",
					"type": "uuid",
					"primaryKey": false,
					"notNull": true
				},
				"joined_at": {
					"name": "joined_at",
					"type": "timestamp",
					"primaryKey": false,
					"notNull": true,
					"default": "now()"
				},
				"updated_at": {
					"name": "updated_at",
					"type": "timestamp",
					"primaryKey": false,
					"notNull": true,
					"default": "now()"
				},
				"created_at": {
					"name": "created_at",
					"type": "timestamp",
					"primaryKey": false,
					"notNull": true,
					"default": "now()"
				},
				"deleted_at": {
					"name": "deleted_at",
					"type": "timestamp",
					"primaryKey": false,
					"notNull": false
				}
			},
			"indexes": {},
			"foreignKeys": {
				"user_groups_user_id_users_id_fk": {
					"name": "user_groups_user_id_users_id_fk",
					"tableFrom": "user_groups",
					"tableTo": "users",
					"columnsFrom": ["user_id"],
					"columnsTo": ["id"],
					"onDelete": "no action",
					"onUpdate": "no action"
				},
				"user_groups_group_id_groups_id_fk": {
					"name": "user_groups_group_id_groups_id_fk",
					"tableFrom": "user_groups",
					"tableTo": "groups",
					"columnsFrom": ["group_id"],
					"columnsTo": ["id"],
					"onDelete": "no action",
					"onUpdate": "no action"
				}
			},
			"compositePrimaryKeys": {},
			"uniqueConstraints": {
				"user_groups_userId_groupId_unique": {
					"name": "user_groups_userId_groupId_unique",
					"nullsNotDistinct": false,
					"columns": ["user_id", "group_id"]
				}
			},
			"policies": {},
			"checkConstraints": {},
			"isRLSEnabled": false
		},
		"public.users": {
			"name": "users",
			"schema": "",
			"columns": {
				"id": {
					"name": "id",
					"type": "uuid",
					"primaryKey": true,
					"notNull": true,
					"default": "gen_random_uuid()"
				},
				"full_name": {
					"name": "full_name",
					"type": "varchar(255)",
					"primaryKey": false,
					"notNull": true
				},
				"display_name": {
					"name": "display_name",
					"type": "varchar(255)",
					"primaryKey": false,
					"notNull": true
				},
				"email": {
					"name": "email",
					"type": "varchar(255)",
					"primaryKey": false,
					"notNull": true
				},
				"password_hash": {
					"name": "password_hash",
					"type": "text",
					"primaryKey": false,
					"notNull": true
				},
				"email_verified_at": {
					"name": "email_verified_at",
					"type": "timestamp",
					"primaryKey": false,
					"notNull": false
				},
				"status": {
					"name": "status",
					"type": "user_status",
					"typeSchema": "public",
					"primaryKey": false,
					"notNull": true,
					"default": "'active'"
				},
				"updated_at": {
					"name": "updated_at",
					"type": "timestamp",
					"primaryKey": false,
					"notNull": true,
					"default": "now()"
				},
				"created_at": {
					"name": "created_at",
					"type": "timestamp",
					"primaryKey": false,
					"notNull": true,
					"default": "now()"
				},
				"deleted_at": {
					"name": "deleted_at",
					"type": "timestamp",
					"primaryKey": false,
					"notNull": false
				}
			},
			"indexes": {
				"email_index": {
					"name": "email_index",
					"columns": [
						{
							"expression": "email",
							"isExpression": false,
							"asc": true,
							"nulls": "last"
						}
					],
					"isUnique": true,
					"concurrently": false,
					"method": "btree",
					"with": {}
				}
			},
			"foreignKeys": {},
			"compositePrimaryKeys": {},
			"uniqueConstraints": {
				"users_displayName_unique": {
					"name": "users_displayName_unique",
					"nullsNotDistinct": false,
					"columns": ["display_name"]
				},
				"users_email_unique": {
					"name": "users_email_unique",
					"nullsNotDistinct": false,
					"columns": ["email"]
				}
			},
			"policies": {},
			"checkConstraints": {},
			"isRLSEnabled": false
		}
	},
	"enums": {
		"public.resource_status": {
			"name": "resource_status",
			"schema": "public",
			"values": ["active", "deleted", "archived"]
		},
		"public.resource_type": {
			"name": "resource_type",
			"schema": "public",
			"values": ["file", "folder"]
		},
		"public.access_level": {
			"name": "access_level",
			"schema": "public",
			"values": ["viewer", "editor", "commenter"]
		},
		"public.entity_type": {
			"name": "entity_type",
			"schema": "public",
			"values": ["user", "group"]
		},
		"public.user_status": {
			"name": "user_status",
			"schema": "public",
			"values": ["active", "inactive", "deleted"]
		}
	},
	"schemas": {},
	"sequences": {},
	"roles": {},
	"policies": {},
	"views": {},
	"_meta": {
		"columns": {},
		"schemas": {},
		"tables": {}
	}
}
